byteguard/__init__.py
byteguard/bot.py
byteguard-0.1.0.dist-info/LICENSE
byteguard-0.1.0.dist-info/METADATA
byteguard-0.1.0.dist-info/WHEEL
byteguard-0.1.0.dist-info/entry_points.txt
byteguard-0.1.0.dist-info/top_level.txt
byteguard-0.1.0.dist-info/RECORD
