Metadata-Version: 2.2
Name: byteguard
Version: 0.1.0
Summary: Discord Security Bot that prevents priviliged people from destroying the server
Author: webgtx
License: BSD 3-Clause License
Project-URL: Source, https://github.com/webgtx/byteguard
Requires-Python: >=3.9
License-File: LICENSE
Requires-Dist: python-dotenv==1.0.0
Requires-Dist: requests==2.31.0
Requires-Dist: discord.py==2.4.0
